{
    "keep": {
        "days": false,
        "amount": 30
    },
    "auditLog": "C:\\Users\\Changhyeon_Lee\\Desktop\\hanhe99\\7_spata_clone_coding\\BACKEND\\logs\\.08b652cad3a6bb45e5f5923edb515b8b04a7de63-audit.json",
    "files": [
        {
            "date": 1661365321685,
            "name": "C:\\Users\\Changhyeon_Lee\\Desktop\\hanhe99\\7_spata_clone_coding\\BACKEND\\logs\\2022-08-25.exception.log",
            "hash": "1357ef235d711fc4826e7356922ceffc279f0806c3c1712c8835a2ce11285f5f"
        }
    ],
    "hashType": "sha256"
}